tests
dateconv
