Metadata-Version: 1.1
Name: python-dateconv
Version: 0.0.9
Summary: Package for date convert between formats 
Home-page: https://github.com/WarmongeR1/python-dateconv
Author: Sapronov Alexander
Author-email: sapronov.alexander92@gmail.com
License: GNU GENERAL PUBLIC LICENSE
